<?xml version="1.0" encoding="utf-8"?>
<annotations>
  <version>1.1</version>
  <meta>
    <job>
      <id>176565</id>
      <size>5</size>
      <mode>annotation</mode>
      <overlap>0</overlap>
      <bugtracker></bugtracker>
      <created>2023-05-30 15:57:07.855548+00:00</created>
      <updated>2023-05-30 16:02:09.316864+00:00</updated>
      <subset>default</subset>
      <start_frame>0</start_frame>
      <stop_frame>4</stop_frame>
      <frame_filter></frame_filter>
      <segments>
        <segment>
          <id>176565</id>
          <start>0</start>
          <stop>4</stop>
          <url>https://app.cvat.ai/api/jobs/176565</url>
        </segment>
      </segments>
      <owner>
        <username>tommycwong</username>
        <email>cwong13@vols.utk.edu</email>
      </owner>
      <assignee>
        <username>tommycwong</username>
        <email>cwong13@vols.utk.edu</email>
      </assignee>
      <labels>
        <label>
          <name>bubble</name>
          <color>#61b21f</color>
          <type>any</type>
          <attributes>
          </attributes>
        </label>
      </labels>
    </job>
    <dumped>2023-05-30 16:02:49.095643+00:00</dumped>
  </meta>
  <image id="0" name="DL_for_Microscopy_Train_Img_2.png" width="512" height="512">
    <polygon label="bubble" source="manual" occluded="0" points="285.70,4.60;274.44,3.97;266.33,10.21;260.09,17.70;256.97,27.68;259.47,37.03;265.70,45.14;274.44,48.89;283.79,52.63;293.15,51.38;301.26,46.39;306.25,37.66;308.74,28.30;306.87,18.95;303.13,10.21;295.02,4.60" z_order="0">
    </polygon>
    <polygon label="bubble" source="manual" occluded="0" points="418.52,91.92;409.17,90.05;399.81,91.30;390.45,93.80;381.72,98.16;377.98,106.89;374.86,116.25;370.49,124.98;369.25,134.34;374.24,143.70;380.47,151.18;387.96,157.42;395.44,163.66;404.80,163.03;414.16,159.91;423.51,158.04;430.37,151.18;436.61,143.07;440.35,134.34;439.11,124.98;437.24,115.63;433.49,106.27;426.63,98.79" z_order="0">
    </polygon>
    <polygon label="bubble" source="manual" occluded="0" points="480.90,137.50;469.05,131.22;459.69,128.10;450.33,129.97;442.23,135.59;435.99,143.07;431.62,152.43;427.26,161.16;422.89,169.89;420.39,179.25;420.39,189.23;425.38,201.08;431.62,208.57;440.35,212.31;449.71,213.56;459.07,214.80;467.18,209.81;475.91,204.82;484.02,199.83;490.26,192.35;494.00,183.62;496.49,174.26;496.49,164.28;494.00,154.92;489.63,146.19" z_order="0">
    </polygon>
    <polygon label="bubble" source="manual" occluded="0" points="310.68,168.46;309.43,178.44;304.44,186.55;297.58,194.03;289.47,200.27;281.98,206.51;274.50,212.75;266.39,217.74;256.41,215.86;247.68,210.87;239.57,205.88;231.46,199.65;224.60,192.79;219.61,184.68;218.98,174.70;218.36,165.34;217.74,155.98;222.10,147.25;228.96,140.39;238.32,136.02;247.05,132.28;257.03,129.79;267.01,127.29;276.99,125.42;285.73,129.79;292.59,136.65;298.82,144.13;304.44,152.24;308.18,160.97" z_order="0">
    </polygon>
    <polygon label="bubble" source="manual" occluded="0" points="132.28,124.80;140.39,119.18;149.75,120.43;159.73,122.93;169.71,125.42;177.82,130.41;185.92,136.65;192.79,144.13;198.40,152.24;200.89,161.60;203.39,170.95;204.01,180.31;200.89,189.67;195.28,198.40;189.04,205.88;184.05,213.99;178.44,222.10;169.08,225.22;159.73,227.72;149.75,228.34;140.39,224.60;132.28,219.61;126.04,212.12;120.43,204.01;116.06,195.28;111.07,187.17;107.33,178.44;104.84,169.08;103.59,159.73;105.46,149.75;110.45,141.64;117.94,135.40;126.04,129.16" z_order="0">
    </polygon>
    <polygon label="bubble" source="manual" occluded="0" points="74.90,150.99;83.63,155.98;90.49,162.85;98.60,168.46;106.71,174.07;112.95,181.56;117.94,189.67;118.56,199.02;117.31,208.38;114.19,217.74;111.07,227.09;102.34,232.71;93.61,236.45;86.75,243.31;79.89,250.17;69.91,252.67;59.93,253.29;49.95,250.17;43.08,243.31;34.35,237.70;25.62,232.08;18.76,224.60;15.02,215.86;16.26,205.88;16.89,196.53;18.76,187.17;23.75,178.44;29.99,170.33;36.85,163.47;44.96,158.48;53.69,154.74;63.67,151.62" z_order="0">
    </polygon>
    <polygon label="bubble" source="manual" occluded="0" points="88.62,321.90;96.73,327.52;102.97,335.00;108.58,343.11;111.07,352.47;107.33,361.20;101.09,368.69;92.36,374.30;83.00,374.92;73.65,375.55;64.29,374.30;56.18,368.06;49.95,360.58;44.96,351.22;43.71,341.86;44.96,331.88;51.19,323.77;59.30,318.16;68.03,314.42;78.01,314.42" z_order="0">
    </polygon>
    <polygon label="bubble" source="manual" occluded="0" points="166.00,340.00;174.10,346.90;179.69,353.09;184.68,361.20;187.17,370.56;183.43,379.29;179.69,388.02;174.70,396.13;165.96,400.50;156.61,402.99;146.63,402.99;138.52,398.00;131.03,391.76;122.93,385.53;116.06,378.67;111.07,370.56;113.57,361.20;117.31,352.47;120.43,343.11;125.42,334.38;132.28,327.52;142.26,327.52;151.62,329.39;160.97,334.38" z_order="0">
    </polygon>
    <polygon label="bubble" source="manual" occluded="0" points="286.97,302.57;296.95,302.57;306.31,305.06;313.17,311.92;319.41,319.41;321.90,328.76;319.41,338.12;316.91,347.48;311.92,355.59;304.44,362.45;295.71,366.81;285.73,366.81;276.37,364.32;268.26,359.33;262.02,351.84;258.90,342.49;255.16,333.75;258.28,324.40;263.27,316.29;270.76,310.05;278.24,303.81" z_order="0">
    </polygon>
    <polygon label="bubble" source="manual" occluded="0" points="512.00,87.73;507.16,79.26;505.29,69.91;505.91,59.93;512.00,52.62" z_order="0">
    </polygon>
    <polygon label="bubble" source="manual" occluded="0" points="56.39,512.00;58.68,509.03;64.92,501.55;74.90,497.80;84.25,495.31;92.98,499.05;99.85,505.91;101.47,512.00" z_order="0">
    </polygon>
    <polygon label="bubble" source="manual" occluded="0" points="238.32,511.53;244.56,504.04;252.04,497.80;261.40,497.18;271.38,496.56;281.36,499.67;291.34,502.17;300.07,507.16;303.05,512.00;240.72,512.00" z_order="0">
    </polygon>
    <polygon label="bubble" source="manual" occluded="0" points="344.98,508.41;338.74,500.30;331.26,493.44;321.90,487.82;311.92,485.33;302.57,484.08;294.46,489.69;286.97,495.93;279.49,502.17;272.63,509.03;272.03,512.00;346.60,511.40" z_order="0">
    </polygon>
    <polygon label="bubble" source="manual" occluded="0" points="393.27,512.00;396.13,503.42;401.74,495.31;408.60,486.00;415.47,481.59;422.95,475.35;432.31,474.10;442.29,472.23;450.40,477.84;457.88,484.08;465.37,490.32;471.61,497.80;477.84,505.29;481.97,512.00" z_order="0">
    </polygon>
  </image>
  <image id="1" name="100kX_300kV_0537_10_2_rot270.png" width="512" height="512">
    <polygon label="bubble" source="manual" occluded="0" points="285.70,4.60;274.44,3.97;266.33,10.21;260.09,17.70;256.97,27.68;259.47,37.03;265.70,45.14;274.44,48.89;283.79,52.63;293.15,51.38;301.26,46.39;306.25,37.66;308.74,28.30;306.87,18.95;303.13,10.21;295.02,4.60" z_order="0">
    </polygon>
    <polygon label="bubble" source="manual" occluded="0" points="418.52,91.92;409.17,90.05;399.81,91.30;390.45,93.80;381.72,98.16;377.98,106.89;374.86,116.25;370.49,124.98;369.25,134.34;374.24,143.70;380.47,151.18;387.96,157.42;395.44,163.66;404.80,163.03;414.16,159.91;423.51,158.04;430.37,151.18;436.61,143.07;440.35,134.34;439.11,124.98;437.24,115.63;433.49,106.27;426.63,98.79" z_order="0">
    </polygon>
    <polygon label="bubble" source="manual" occluded="0" points="480.90,137.50;469.05,131.22;459.69,128.10;450.33,129.97;442.23,135.59;435.99,143.07;431.62,152.43;427.26,161.16;422.89,169.89;420.39,179.25;420.39,189.23;425.38,201.08;431.62,208.57;440.35,212.31;449.71,213.56;459.07,214.80;467.18,209.81;475.91,204.82;484.02,199.83;490.26,192.35;494.00,183.62;496.49,174.26;496.49,164.28;494.00,154.92;489.63,146.19" z_order="0">
    </polygon>
    <polygon label="bubble" source="manual" occluded="0" points="310.68,168.46;309.43,178.44;304.44,186.55;297.58,194.03;289.47,200.27;281.98,206.51;274.50,212.75;266.39,217.74;256.41,215.86;247.68,210.87;239.57,205.88;231.46,199.65;224.60,192.79;219.61,184.68;218.98,174.70;218.36,165.34;217.74,155.98;222.10,147.25;228.96,140.39;238.32,136.02;247.05,132.28;257.03,129.79;267.01,127.29;276.99,125.42;285.73,129.79;292.59,136.65;298.82,144.13;304.44,152.24;308.18,160.97" z_order="0">
    </polygon>
    <polygon label="bubble" source="manual" occluded="0" points="132.28,124.80;140.39,119.18;149.75,120.43;159.73,122.93;169.71,125.42;177.82,130.41;185.92,136.65;192.79,144.13;198.40,152.24;200.89,161.60;203.39,170.95;204.01,180.31;200.89,189.67;195.28,198.40;189.04,205.88;184.05,213.99;178.44,222.10;169.08,225.22;159.73,227.72;149.75,228.34;140.39,224.60;132.28,219.61;126.04,212.12;120.43,204.01;116.06,195.28;111.07,187.17;107.33,178.44;104.84,169.08;103.59,159.73;105.46,149.75;110.45,141.64;117.94,135.40;126.04,129.16" z_order="0">
    </polygon>
    <polygon label="bubble" source="manual" occluded="0" points="74.90,150.99;83.63,155.98;90.49,162.85;98.60,168.46;106.71,174.07;112.95,181.56;117.94,189.67;118.56,199.02;117.31,208.38;114.19,217.74;111.07,227.09;102.34,232.71;93.61,236.45;86.75,243.31;79.89,250.17;69.91,252.67;59.93,253.29;49.95,250.17;43.08,243.31;34.35,237.70;25.62,232.08;18.76,224.60;15.02,215.86;16.26,205.88;16.89,196.53;18.76,187.17;23.75,178.44;29.99,170.33;36.85,163.47;44.96,158.48;53.69,154.74;63.67,151.62" z_order="0">
    </polygon>
    <polygon label="bubble" source="manual" occluded="0" points="88.62,321.90;96.73,327.52;102.97,335.00;108.58,343.11;111.07,352.47;107.33,361.20;101.09,368.69;92.36,374.30;83.00,374.92;73.65,375.55;64.29,374.30;56.18,368.06;49.95,360.58;44.96,351.22;43.71,341.86;44.96,331.88;51.19,323.77;59.30,318.16;68.03,314.42;78.01,314.42" z_order="0">
    </polygon>
    <polygon label="bubble" source="manual" occluded="0" points="166.00,340.00;174.10,346.90;179.69,353.09;184.68,361.20;187.17,370.56;183.43,379.29;179.69,388.02;174.70,396.13;165.96,400.50;156.61,402.99;146.63,402.99;138.52,398.00;131.03,391.76;122.93,385.53;116.06,378.67;111.07,370.56;113.57,361.20;117.31,352.47;120.43,343.11;125.42,334.38;132.28,327.52;142.26,327.52;151.62,329.39;160.97,334.38" z_order="0">
    </polygon>
    <polygon label="bubble" source="manual" occluded="0" points="286.97,302.57;296.95,302.57;306.31,305.06;313.17,311.92;319.41,319.41;321.90,328.76;319.41,338.12;316.91,347.48;311.92,355.59;304.44,362.45;295.71,366.81;285.73,366.81;276.37,364.32;268.26,359.33;262.02,351.84;258.90,342.49;255.16,333.75;258.28,324.40;263.27,316.29;270.76,310.05;278.24,303.81" z_order="0">
    </polygon>
    <polygon label="bubble" source="manual" occluded="0" points="512.00,87.73;507.16,79.26;505.29,69.91;505.91,59.93;512.00,52.62" z_order="0">
    </polygon>
    <polygon label="bubble" source="manual" occluded="0" points="56.39,512.00;58.68,509.03;64.92,501.55;74.90,497.80;84.25,495.31;92.98,499.05;99.85,505.91;101.47,512.00" z_order="0">
    </polygon>
    <polygon label="bubble" source="manual" occluded="0" points="238.32,511.53;244.56,504.04;252.04,497.80;261.40,497.18;271.38,496.56;281.36,499.67;291.34,502.17;300.07,507.16;303.05,512.00;240.72,512.00" z_order="0">
    </polygon>
    <polygon label="bubble" source="manual" occluded="0" points="344.98,508.41;338.74,500.30;331.26,493.44;321.90,487.82;311.92,485.33;302.57,484.08;294.46,489.69;286.97,495.93;279.49,502.17;272.63,509.03;272.03,512.00;346.60,511.40" z_order="0">
    </polygon>
    <polygon label="bubble" source="manual" occluded="0" points="393.27,512.00;396.13,503.42;401.74,495.31;408.60,486.00;415.47,481.59;422.95,475.35;432.31,474.10;442.29,472.23;450.40,477.84;457.88,484.08;465.37,490.32;471.61,497.80;477.84,505.29;481.97,512.00" z_order="0">
    </polygon>
  </image>
  <image id="2" name="100kX_300kV_0537_11_1_rot180.png" width="512" height="512">
    <polygon label="bubble" source="manual" occluded="0" points="285.70,4.60;274.44,3.97;266.33,10.21;260.09,17.70;256.97,27.68;259.47,37.03;265.70,45.14;274.44,48.89;283.79,52.63;293.15,51.38;301.26,46.39;306.25,37.66;308.74,28.30;306.87,18.95;303.13,10.21;295.02,4.60" z_order="0">
    </polygon>
    <polygon label="bubble" source="manual" occluded="0" points="418.52,91.92;409.17,90.05;399.81,91.30;390.45,93.80;381.72,98.16;377.98,106.89;374.86,116.25;370.49,124.98;369.25,134.34;374.24,143.70;380.47,151.18;387.96,157.42;395.44,163.66;404.80,163.03;414.16,159.91;423.51,158.04;430.37,151.18;436.61,143.07;440.35,134.34;439.11,124.98;437.24,115.63;433.49,106.27;426.63,98.79" z_order="0">
    </polygon>
    <polygon label="bubble" source="manual" occluded="0" points="480.90,137.50;469.05,131.22;459.69,128.10;450.33,129.97;442.23,135.59;435.99,143.07;431.62,152.43;427.26,161.16;422.89,169.89;420.39,179.25;420.39,189.23;425.38,201.08;431.62,208.57;440.35,212.31;449.71,213.56;459.07,214.80;467.18,209.81;475.91,204.82;484.02,199.83;490.26,192.35;494.00,183.62;496.49,174.26;496.49,164.28;494.00,154.92;489.63,146.19" z_order="0">
    </polygon>
    <polygon label="bubble" source="manual" occluded="0" points="310.68,168.46;309.43,178.44;304.44,186.55;297.58,194.03;289.47,200.27;281.98,206.51;274.50,212.75;266.39,217.74;256.41,215.86;247.68,210.87;239.57,205.88;231.46,199.65;224.60,192.79;219.61,184.68;218.98,174.70;218.36,165.34;217.74,155.98;222.10,147.25;228.96,140.39;238.32,136.02;247.05,132.28;257.03,129.79;267.01,127.29;276.99,125.42;285.73,129.79;292.59,136.65;298.82,144.13;304.44,152.24;308.18,160.97" z_order="0">
    </polygon>
    <polygon label="bubble" source="manual" occluded="0" points="132.28,124.80;140.39,119.18;149.75,120.43;159.73,122.93;169.71,125.42;177.82,130.41;185.92,136.65;192.79,144.13;198.40,152.24;200.89,161.60;203.39,170.95;204.01,180.31;200.89,189.67;195.28,198.40;189.04,205.88;184.05,213.99;178.44,222.10;169.08,225.22;159.73,227.72;149.75,228.34;140.39,224.60;132.28,219.61;126.04,212.12;120.43,204.01;116.06,195.28;111.07,187.17;107.33,178.44;104.84,169.08;103.59,159.73;105.46,149.75;110.45,141.64;117.94,135.40;126.04,129.16" z_order="0">
    </polygon>
    <polygon label="bubble" source="manual" occluded="0" points="74.90,150.99;83.63,155.98;90.49,162.85;98.60,168.46;106.71,174.07;112.95,181.56;117.94,189.67;118.56,199.02;117.31,208.38;114.19,217.74;111.07,227.09;102.34,232.71;93.61,236.45;86.75,243.31;79.89,250.17;69.91,252.67;59.93,253.29;49.95,250.17;43.08,243.31;34.35,237.70;25.62,232.08;18.76,224.60;15.02,215.86;16.26,205.88;16.89,196.53;18.76,187.17;23.75,178.44;29.99,170.33;36.85,163.47;44.96,158.48;53.69,154.74;63.67,151.62" z_order="0">
    </polygon>
    <polygon label="bubble" source="manual" occluded="0" points="88.62,321.90;96.73,327.52;102.97,335.00;108.58,343.11;111.07,352.47;107.33,361.20;101.09,368.69;92.36,374.30;83.00,374.92;73.65,375.55;64.29,374.30;56.18,368.06;49.95,360.58;44.96,351.22;43.71,341.86;44.96,331.88;51.19,323.77;59.30,318.16;68.03,314.42;78.01,314.42" z_order="0">
    </polygon>
    <polygon label="bubble" source="manual" occluded="0" points="166.00,340.00;174.10,346.90;179.69,353.09;184.68,361.20;187.17,370.56;183.43,379.29;179.69,388.02;174.70,396.13;165.96,400.50;156.61,402.99;146.63,402.99;138.52,398.00;131.03,391.76;122.93,385.53;116.06,378.67;111.07,370.56;113.57,361.20;117.31,352.47;120.43,343.11;125.42,334.38;132.28,327.52;142.26,327.52;151.62,329.39;160.97,334.38" z_order="0">
    </polygon>
    <polygon label="bubble" source="manual" occluded="0" points="286.97,302.57;296.95,302.57;306.31,305.06;313.17,311.92;319.41,319.41;321.90,328.76;319.41,338.12;316.91,347.48;311.92,355.59;304.44,362.45;295.71,366.81;285.73,366.81;276.37,364.32;268.26,359.33;262.02,351.84;258.90,342.49;255.16,333.75;258.28,324.40;263.27,316.29;270.76,310.05;278.24,303.81" z_order="0">
    </polygon>
    <polygon label="bubble" source="manual" occluded="0" points="512.00,87.73;507.16,79.26;505.29,69.91;505.91,59.93;512.00,52.62" z_order="0">
    </polygon>
    <polygon label="bubble" source="manual" occluded="0" points="56.39,512.00;58.68,509.03;64.92,501.55;74.90,497.80;84.25,495.31;92.98,499.05;99.85,505.91;101.47,512.00" z_order="0">
    </polygon>
    <polygon label="bubble" source="manual" occluded="0" points="238.32,511.53;244.56,504.04;252.04,497.80;261.40,497.18;271.38,496.56;281.36,499.67;291.34,502.17;300.07,507.16;303.05,512.00;240.72,512.00" z_order="0">
    </polygon>
    <polygon label="bubble" source="manual" occluded="0" points="344.98,508.41;338.74,500.30;331.26,493.44;321.90,487.82;311.92,485.33;302.57,484.08;294.46,489.69;286.97,495.93;279.49,502.17;272.63,509.03;272.03,512.00;346.60,511.40" z_order="0">
    </polygon>
    <polygon label="bubble" source="manual" occluded="0" points="393.27,512.00;396.13,503.42;401.74,495.31;408.60,486.00;415.47,481.59;422.95,475.35;432.31,474.10;442.29,472.23;450.40,477.84;457.88,484.08;465.37,490.32;471.61,497.80;477.84,505.29;481.97,512.00" z_order="0">
    </polygon>
  </image>
  <image id="3" name="100kX_300kV_0537_16_0_rot180.png" width="512" height="512">
    <polygon label="bubble" source="manual" occluded="0" points="285.70,4.60;274.44,3.97;266.33,10.21;260.09,17.70;256.97,27.68;259.47,37.03;265.70,45.14;274.44,48.89;283.79,52.63;293.15,51.38;301.26,46.39;306.25,37.66;308.74,28.30;306.87,18.95;303.13,10.21;295.02,4.60" z_order="0">
    </polygon>
    <polygon label="bubble" source="manual" occluded="0" points="418.52,91.92;409.17,90.05;399.81,91.30;390.45,93.80;381.72,98.16;377.98,106.89;374.86,116.25;370.49,124.98;369.25,134.34;374.24,143.70;380.47,151.18;387.96,157.42;395.44,163.66;404.80,163.03;414.16,159.91;423.51,158.04;430.37,151.18;436.61,143.07;440.35,134.34;439.11,124.98;437.24,115.63;433.49,106.27;426.63,98.79" z_order="0">
    </polygon>
    <polygon label="bubble" source="manual" occluded="0" points="480.90,137.50;469.05,131.22;459.69,128.10;450.33,129.97;442.23,135.59;435.99,143.07;431.62,152.43;427.26,161.16;422.89,169.89;420.39,179.25;420.39,189.23;425.38,201.08;431.62,208.57;440.35,212.31;449.71,213.56;459.07,214.80;467.18,209.81;475.91,204.82;484.02,199.83;490.26,192.35;494.00,183.62;496.49,174.26;496.49,164.28;494.00,154.92;489.63,146.19" z_order="0">
    </polygon>
    <polygon label="bubble" source="manual" occluded="0" points="310.68,168.46;309.43,178.44;304.44,186.55;297.58,194.03;289.47,200.27;281.98,206.51;274.50,212.75;266.39,217.74;256.41,215.86;247.68,210.87;239.57,205.88;231.46,199.65;224.60,192.79;219.61,184.68;218.98,174.70;218.36,165.34;217.74,155.98;222.10,147.25;228.96,140.39;238.32,136.02;247.05,132.28;257.03,129.79;267.01,127.29;276.99,125.42;285.73,129.79;292.59,136.65;298.82,144.13;304.44,152.24;308.18,160.97" z_order="0">
    </polygon>
    <polygon label="bubble" source="manual" occluded="0" points="132.28,124.80;140.39,119.18;149.75,120.43;159.73,122.93;169.71,125.42;177.82,130.41;185.92,136.65;192.79,144.13;198.40,152.24;200.89,161.60;203.39,170.95;204.01,180.31;200.89,189.67;195.28,198.40;189.04,205.88;184.05,213.99;178.44,222.10;169.08,225.22;159.73,227.72;149.75,228.34;140.39,224.60;132.28,219.61;126.04,212.12;120.43,204.01;116.06,195.28;111.07,187.17;107.33,178.44;104.84,169.08;103.59,159.73;105.46,149.75;110.45,141.64;117.94,135.40;126.04,129.16" z_order="0">
    </polygon>
    <polygon label="bubble" source="manual" occluded="0" points="74.90,150.99;83.63,155.98;90.49,162.85;98.60,168.46;106.71,174.07;112.95,181.56;117.94,189.67;118.56,199.02;117.31,208.38;114.19,217.74;111.07,227.09;102.34,232.71;93.61,236.45;86.75,243.31;79.89,250.17;69.91,252.67;59.93,253.29;49.95,250.17;43.08,243.31;34.35,237.70;25.62,232.08;18.76,224.60;15.02,215.86;16.26,205.88;16.89,196.53;18.76,187.17;23.75,178.44;29.99,170.33;36.85,163.47;44.96,158.48;53.69,154.74;63.67,151.62" z_order="0">
    </polygon>
    <polygon label="bubble" source="manual" occluded="0" points="88.62,321.90;96.73,327.52;102.97,335.00;108.58,343.11;111.07,352.47;107.33,361.20;101.09,368.69;92.36,374.30;83.00,374.92;73.65,375.55;64.29,374.30;56.18,368.06;49.95,360.58;44.96,351.22;43.71,341.86;44.96,331.88;51.19,323.77;59.30,318.16;68.03,314.42;78.01,314.42" z_order="0">
    </polygon>
    <polygon label="bubble" source="manual" occluded="0" points="166.00,340.00;174.10,346.90;179.69,353.09;184.68,361.20;187.17,370.56;183.43,379.29;179.69,388.02;174.70,396.13;165.96,400.50;156.61,402.99;146.63,402.99;138.52,398.00;131.03,391.76;122.93,385.53;116.06,378.67;111.07,370.56;113.57,361.20;117.31,352.47;120.43,343.11;125.42,334.38;132.28,327.52;142.26,327.52;151.62,329.39;160.97,334.38" z_order="0">
    </polygon>
    <polygon label="bubble" source="manual" occluded="0" points="286.97,302.57;296.95,302.57;306.31,305.06;313.17,311.92;319.41,319.41;321.90,328.76;319.41,338.12;316.91,347.48;311.92,355.59;304.44,362.45;295.71,366.81;285.73,366.81;276.37,364.32;268.26,359.33;262.02,351.84;258.90,342.49;255.16,333.75;258.28,324.40;263.27,316.29;270.76,310.05;278.24,303.81" z_order="0">
    </polygon>
    <polygon label="bubble" source="manual" occluded="0" points="512.00,87.73;507.16,79.26;505.29,69.91;505.91,59.93;512.00,52.62" z_order="0">
    </polygon>
    <polygon label="bubble" source="manual" occluded="0" points="56.39,512.00;58.68,509.03;64.92,501.55;74.90,497.80;84.25,495.31;92.98,499.05;99.85,505.91;101.47,512.00" z_order="0">
    </polygon>
    <polygon label="bubble" source="manual" occluded="0" points="238.32,511.53;244.56,504.04;252.04,497.80;261.40,497.18;271.38,496.56;281.36,499.67;291.34,502.17;300.07,507.16;303.05,512.00;240.72,512.00" z_order="0">
    </polygon>
    <polygon label="bubble" source="manual" occluded="0" points="344.98,508.41;338.74,500.30;331.26,493.44;321.90,487.82;311.92,485.33;302.57,484.08;294.46,489.69;286.97,495.93;279.49,502.17;272.63,509.03;272.03,512.00;346.60,511.40" z_order="0">
    </polygon>
    <polygon label="bubble" source="manual" occluded="0" points="393.27,512.00;396.13,503.42;401.74,495.31;408.60,486.00;415.47,481.59;422.95,475.35;432.31,474.10;442.29,472.23;450.40,477.84;457.88,484.08;465.37,490.32;471.61,497.80;477.84,505.29;481.97,512.00" z_order="0">
    </polygon>
  </image>
  <image id="4" name="100kX_300kV_0537_2_3_flip.png" width="512" height="512">
    <polygon label="bubble" source="manual" occluded="0" points="285.70,4.60;274.44,3.97;266.33,10.21;260.09,17.70;256.97,27.68;259.47,37.03;265.70,45.14;274.44,48.89;283.79,52.63;293.15,51.38;301.26,46.39;306.25,37.66;308.74,28.30;306.87,18.95;303.13,10.21;295.02,4.60" z_order="0">
    </polygon>
    <polygon label="bubble" source="manual" occluded="0" points="418.52,91.92;409.17,90.05;399.81,91.30;390.45,93.80;381.72,98.16;377.98,106.89;374.86,116.25;370.49,124.98;369.25,134.34;374.24,143.70;380.47,151.18;387.96,157.42;395.44,163.66;404.80,163.03;414.16,159.91;423.51,158.04;430.37,151.18;436.61,143.07;440.35,134.34;439.11,124.98;437.24,115.63;433.49,106.27;426.63,98.79" z_order="0">
    </polygon>
    <polygon label="bubble" source="manual" occluded="0" points="480.90,137.50;469.05,131.22;459.69,128.10;450.33,129.97;442.23,135.59;435.99,143.07;431.62,152.43;427.26,161.16;422.89,169.89;420.39,179.25;420.39,189.23;425.38,201.08;431.62,208.57;440.35,212.31;449.71,213.56;459.07,214.80;467.18,209.81;475.91,204.82;484.02,199.83;490.26,192.35;494.00,183.62;496.49,174.26;496.49,164.28;494.00,154.92;489.63,146.19" z_order="0">
    </polygon>
    <polygon label="bubble" source="manual" occluded="0" points="310.68,168.46;309.43,178.44;304.44,186.55;297.58,194.03;289.47,200.27;281.98,206.51;274.50,212.75;266.39,217.74;256.41,215.86;247.68,210.87;239.57,205.88;231.46,199.65;224.60,192.79;219.61,184.68;218.98,174.70;218.36,165.34;217.74,155.98;222.10,147.25;228.96,140.39;238.32,136.02;247.05,132.28;257.03,129.79;267.01,127.29;276.99,125.42;285.73,129.79;292.59,136.65;298.82,144.13;304.44,152.24;308.18,160.97" z_order="0">
    </polygon>
    <polygon label="bubble" source="manual" occluded="0" points="132.28,124.80;140.39,119.18;149.75,120.43;159.73,122.93;169.71,125.42;177.82,130.41;185.92,136.65;192.79,144.13;198.40,152.24;200.89,161.60;203.39,170.95;204.01,180.31;200.89,189.67;195.28,198.40;189.04,205.88;184.05,213.99;178.44,222.10;169.08,225.22;159.73,227.72;149.75,228.34;140.39,224.60;132.28,219.61;126.04,212.12;120.43,204.01;116.06,195.28;111.07,187.17;107.33,178.44;104.84,169.08;103.59,159.73;105.46,149.75;110.45,141.64;117.94,135.40;126.04,129.16" z_order="0">
    </polygon>
    <polygon label="bubble" source="manual" occluded="0" points="74.90,150.99;83.63,155.98;90.49,162.85;98.60,168.46;106.71,174.07;112.95,181.56;117.94,189.67;118.56,199.02;117.31,208.38;114.19,217.74;111.07,227.09;102.34,232.71;93.61,236.45;86.75,243.31;79.89,250.17;69.91,252.67;59.93,253.29;49.95,250.17;43.08,243.31;34.35,237.70;25.62,232.08;18.76,224.60;15.02,215.86;16.26,205.88;16.89,196.53;18.76,187.17;23.75,178.44;29.99,170.33;36.85,163.47;44.96,158.48;53.69,154.74;63.67,151.62" z_order="0">
    </polygon>
    <polygon label="bubble" source="manual" occluded="0" points="88.62,321.90;96.73,327.52;102.97,335.00;108.58,343.11;111.07,352.47;107.33,361.20;101.09,368.69;92.36,374.30;83.00,374.92;73.65,375.55;64.29,374.30;56.18,368.06;49.95,360.58;44.96,351.22;43.71,341.86;44.96,331.88;51.19,323.77;59.30,318.16;68.03,314.42;78.01,314.42" z_order="0">
    </polygon>
    <polygon label="bubble" source="manual" occluded="0" points="166.00,340.00;174.10,346.90;179.69,353.09;184.68,361.20;187.17,370.56;183.43,379.29;179.69,388.02;174.70,396.13;165.96,400.50;156.61,402.99;146.63,402.99;138.52,398.00;131.03,391.76;122.93,385.53;116.06,378.67;111.07,370.56;113.57,361.20;117.31,352.47;120.43,343.11;125.42,334.38;132.28,327.52;142.26,327.52;151.62,329.39;160.97,334.38" z_order="0">
    </polygon>
    <polygon label="bubble" source="manual" occluded="0" points="286.97,302.57;296.95,302.57;306.31,305.06;313.17,311.92;319.41,319.41;321.90,328.76;319.41,338.12;316.91,347.48;311.92,355.59;304.44,362.45;295.71,366.81;285.73,366.81;276.37,364.32;268.26,359.33;262.02,351.84;258.90,342.49;255.16,333.75;258.28,324.40;263.27,316.29;270.76,310.05;278.24,303.81" z_order="0">
    </polygon>
    <polygon label="bubble" source="manual" occluded="0" points="512.00,87.73;507.16,79.26;505.29,69.91;505.91,59.93;512.00,52.62" z_order="0">
    </polygon>
    <polygon label="bubble" source="manual" occluded="0" points="56.39,512.00;58.68,509.03;64.92,501.55;74.90,497.80;84.25,495.31;92.98,499.05;99.85,505.91;101.47,512.00" z_order="0">
    </polygon>
    <polygon label="bubble" source="manual" occluded="0" points="238.32,511.53;244.56,504.04;252.04,497.80;261.40,497.18;271.38,496.56;281.36,499.67;291.34,502.17;300.07,507.16;303.05,512.00;240.72,512.00" z_order="0">
    </polygon>
    <polygon label="bubble" source="manual" occluded="0" points="344.98,508.41;338.74,500.30;331.26,493.44;321.90,487.82;311.92,485.33;302.57,484.08;294.46,489.69;286.97,495.93;279.49,502.17;272.63,509.03;272.03,512.00;346.60,511.40" z_order="0">
    </polygon>
    <polygon label="bubble" source="manual" occluded="0" points="393.27,512.00;396.13,503.42;401.74,495.31;408.60,486.00;415.47,481.59;422.95,475.35;432.31,474.10;442.29,472.23;450.40,477.84;457.88,484.08;465.37,490.32;471.61,497.80;477.84,505.29;481.97,512.00" z_order="0">
    </polygon>
  </image>
</annotations>
